ippic/__init__.py
ippic/__main__.py
ippic/data.py
ippic/ipv4.py
ippic/ipv6.py
ippic/util.py
ippic-0.0.1.dist-info/LICENSE
ippic-0.0.1.dist-info/METADATA
ippic-0.0.1.dist-info/WHEEL
ippic-0.0.1.dist-info/entry_points.txt
ippic-0.0.1.dist-info/top_level.txt
ippic-0.0.1.dist-info/RECORD
