Metadata-Version: 2.1
Name: ippic
Version: 0.0.1
Summary: Create an image from an IP address
Home-page: https://github.com/0xflotus/ippic
Author: 0xflotus
Author-email: 0xflotus+pypi@gmail.com
License: MIT
Platform: UNKNOWN
Classifier: License :: OSI Approved :: MIT License
Classifier: Programming Language :: Python :: 3
Classifier: Programming Language :: Python :: 3.9
License-File: LICENSE
Requires-Dist: argparse
Requires-Dist: netaddr
Requires-Dist: Pillow
